roolink_sdk/__init__.py
roolink_sdk/client.py
roolink_sdk/utils.py
roolink_sdk-1.0.1.dist-info/LICENSE
roolink_sdk-1.0.1.dist-info/METADATA
roolink_sdk-1.0.1.dist-info/WHEEL
roolink_sdk-1.0.1.dist-info/top_level.txt
roolink_sdk-1.0.1.dist-info/RECORD
