Metadata-Version: 2.1
Name: roolink-sdk
Version: 1.0.1
Summary: A Python SDK for interacting with the RooLink API
Home-page: https://github.com/RooLinkIO/roolink-sdk-py
License: MIT
Classifier: Programming Language :: Python :: 3
Classifier: License :: OSI Approved :: MIT License
Classifier: Operating System :: OS Independent
Requires-Python: >=3.6
License-File: LICENSE
Requires-Dist: requests>=2.20.0
